drivers/__init__.py
drivers/bme.py
drivers/bmeconstants.py
drivers/bno.py
drivers/si.py
drivers/si1145.py
drivers/si114x.py
unisat-0.1.0.dist-info/LICENSE
unisat-0.1.0.dist-info/METADATA
unisat-0.1.0.dist-info/WHEEL
unisat-0.1.0.dist-info/top_level.txt
unisat-0.1.0.dist-info/RECORD
