Metadata-Version: 2.1
Name: unisat
Version: 0.1.0
Summary: UniSat Software Environtment for Python
Home-page: https://github.com/unisatkz/USK
Author: Yaakov Azat
Author-email: yaakovazat@gmail.com
License: Copyright (c) 2020, UniSat
